{
  "光": {
    "息苦しい": 0.002,
    "美味しい": 0.002,
    "嬉しい": 0.012,
    "強い": 0.034,
    "早い": 0.012,
    "白い": 0.006,
    "遅い": 0.006,
    "鋭い": 0.002,
    "柔らかい": 0.002,
    "くい": 0.002,
    "欲しい": 0.016,
    "いい": 0.044,
    "美しい": 0.002,
    "若い": 0.002,
    "良い": 0.032,
    "辛い": 0.006,
    "弱い": 0.002,
    "ない": 0.088,
    "明るい": 0.006,
    "無い": 0.012,
    "何気ない": 0.002,
    "高い": 0.004,
    "安い": 0.004,
    "浅い": 0.002,
    "すばらしい": 0.004,
    "あたたかい": 0.002,
    "難しい": 0.004,
    "すごい": 0.012,
    "ったらしい": 0.002,
    "埃っぽい": 0.002,
    "上手い": 0.004,
    "可愛い": 0.01,
    "うれしい": 0.004,
    "薄い": 0.006,
    "すっごい": 0.002,
    "優しい": 0.004,
    "ださい": 0.002,
    "多い": 0.004,
    "痛い": 0.008,
    "まぶしい": 0.004,
    "輝かしい": 0.002,
    "偉い": 0.002,
    "えらい": 0.002,
    "おかしい": 0.012,
    "黒い": 0.006,
    "熱い": 0.002,
    "づらい": 0.002,
    "かっこいい": 0.006,
    "悪い": 0.006,
    "ええ": 0.002,
    "眩しい": 0.006,
    "凄い": 0.012,
    "青い": 0.002,
    "少ない": 0.01,
    "貴い": 0.002,
    "深い": 0.004,
    "怖い": 0.004,
    "やすい": 0.008,
    "はやい": 0.002,
    "寒い": 0.002,
    "つらい": 0.004,
    "固い": 0.002,
    "長い": 0.008,
    "まるい": 0.002,
    "楽しい": 0.004,
    "暗い": 0.014,
    "詳しい": 0.002,
    "悪しい": 0.002,
    "かわいい": 0.01,
    "からい": 0.002,
    "ほしい": 0.002,
    "素晴らしい": 0.002,
    "甘い": 0.004,
    "水っぽい": 0.002,
    "くどい": 0.002,
    "善い": 0.002,
    "ほの暗い": 0.004,
    "申し訳ない": 0.002,
    "果てしない": 0.002,
    "しょっぱい": 0.002,
    "面白い": 0.006,
    "よい": 0.006,
    "恥ずかしい": 0.002,
    "ものすごい": 0.002,
    "新しい": 0.002,
    "寂しい": 0.002,
    "温かい": 0.004,
    "苦しい": 0.004,
    "暖かい": 0.004,
    "っぽい": 0.004,
    "尊い": 0.004,
    "やばい": 0.004,
    "おもろい": 0.002,
    "にくい": 0.002,
    "丸い": 0.002,
    "眩い": 0.002,
    "ひどい": 0.002,
    "青白い": 0.002,
    "ボロい": 0.002,
    "黄色い": 0.002,
    "いさぎよい": 0.002,
    "恐ろしい": 0.002,
    "大きい": 0.004,
    "格好いい": 0.002,
    "悲しい": 0.002,
    "厳しい": 0.002,
    "腹黒い": 0.002,
    "きつい": 0.002,
    "おしい": 0.002,
    "こい": 0.002,
    "速い": 0.002,
    "懐かしい": 0.002,
    "よろしい": 0.002,
    "淡い": 0.002,
    "茶色い": 0.002
  }
}