{
  "赤い鳥": {
    "若い": 0.002,
    "すごい": 0.018,
    "良い": 0.014,
    "赤い": 0.3,
    "黄色い": 0.008,
    "ない": 0.046,
    "上手い": 0.004,
    "何気ない": 0.002,
    "粗い": 0.002,
    "でかい": 0.002,
    "悪い": 0.006,
    "いい": 0.032,
    "暖かい": 0.004,
    "細かい": 0.004,
    "明るい": 0.002,
    "太い": 0.006,
    "強い": 0.006,
    "柔らかい": 0.004,
    "面白い": 0.006,
    "青い": 0.008,
    "美味しい": 0.008,
    "多い": 0.008,
    "薄い": 0.004,
    "茶色い": 0.002,
    "可愛い": 0.024,
    "やすい": 0.016,
    "怖い": 0.006,
    "美しい": 0.01,
    "近い": 0.022,
    "白い": 0.014,
    "眠い": 0.002,
    "かわいい": 0.012,
    "遠い": 0.002,
    "しぶとい": 0.002,
    "欲しい": 0.004,
    "うれしい": 0.01,
    "すばやい": 0.002,
    "固い": 0.002,
    "寂しい": 0.002,
    "嬉しい": 0.012,
    "長い": 0.002,
    "親しい": 0.002,
    "楽しい": 0.002,
    "かっこよい": 0.002,
    "かっこいい": 0.006,
    "遅い": 0.002,
    "優しい": 0.004,
    "悲しい": 0.002,
    "懐かしい": 0.002,
    "おいしい": 0.002,
    "黒い": 0.014,
    "っぽい": 0.006,
    "羨ましい": 0.002,
    "感慨深い": 0.002,
    "よい": 0.014,
    "なつかしい": 0.002,
    "難しい": 0.002,
    "幼い": 0.004,
    "恐ろしい": 0.002,
    "広い": 0.002,
    "にくい": 0.002,
    "早い": 0.002,
    "わびしい": 0.002,
    "辛い": 0.004,
    "大きい": 0.006,
    "痒い": 0.002,
    "深い": 0.002,
    "気だるい": 0.002,
    "ままならない": 0.002,
    "軽い": 0.002,
    "わるい": 0.002,
    "重苦しい": 0.002,
    "憂い": 0.002,
    "めでたい": 0.002,
    "たかい": 0.002,
    "なるい": 0.002,
    "あさい": 0.002,
    "宜しい": 0.002,
    "ほしい": 0.006,
    "すっごい": 0.002,
    "寒い": 0.006,
    "ゆるい": 0.002,
    "素晴らしい": 0.002,
    "気味が悪い": 0.002,
    "少ない": 0.002,
    "あおい": 0.002,
    "凄い": 0.002,
    "ボロい": 0.002,
    "くさい": 0.002,
    "忙しい": 0.002,
    "おかしい": 0.002,
    "安い": 0.002,
    "高い": 0.004,
    "賢い": 0.002,
    "うらやましい": 0.002,
    "古い": 0.002,
    "やばい": 0.002,
    "くい": 0.002
  }
}