{
  "休憩": {
    "美味しい": 0.006,
    "小さい": 0.002,
    "ない": 0.058,
    "新しい": 0.004,
    "上手い": 0.004,
    "悔しい": 0.002,
    "面白い": 0.012,
    "楽しい": 0.034,
    "いい": 0.046,
    "良い": 0.034,
    "赤い": 0.002,
    "おもい": 0.004,
    "欲しい": 0.006,
    "つらい": 0.002,
    "うい": 0.004,
    "凄い": 0.004,
    "遅い": 0.008,
    "可愛い": 0.018,
    "懐かしい": 0.006,
    "ずるい": 0.004,
    "無い": 0.012,
    "すごい": 0.012,
    "悪い": 0.016,
    "忙しい": 0.014,
    "眠い": 0.006,
    "多い": 0.016,
    "正しい": 0.002,
    "嬉しい": 0.008,
    "怖い": 0.012,
    "よい": 0.016,
    "苦しい": 0.002,
    "暑い": 0.002,
    "おおい": 0.006,
    "長い": 0.01,
    "痛い": 0.008,
    "優しい": 0.002,
    "甘い": 0.004,
    "熱い": 0.002,
    "広い": 0.002,
    "しんどい": 0.008,
    "やばい": 0.006,
    "くい": 0.002,
    "物凄い": 0.002,
    "うれしい": 0.004,
    "やすい": 0.004,
    "軽い": 0.004,
    "少ない": 0.004,
    "おもろい": 0.002,
    "ありがたい": 0.002,
    "重い": 0.004,
    "遠い": 0.002,
    "まずい": 0.002,
    "恋しい": 0.002,
    "強い": 0.002,
    "かわゆい": 0.004,
    "かっこいい": 0.002,
    "早い": 0.012,
    "格好いい": 0.002,
    "安い": 0.002,
    "ちっちゃい": 0.002,
    "すっごい": 0.002,
    "深い": 0.004,
    "硬い": 0.002,
    "呆気ない": 0.002,
    "っぽい": 0.002,
    "短い": 0.004,
    "かわいい": 0.002,
    "細い": 0.002,
    "詳しい": 0.002,
    "ぽい": 0.002,
    "清い": 0.002,
    "有難い": 0.002,
    "めでたい": 0.002,
    "激しい": 0.002,
    "寒い": 0.004,
    "近い": 0.002,
    "大人っぽい": 0.002,
    "でかい": 0.002,
    "有り難い": 0.002,
    "きつい": 0.002,
    "黄色い": 0.002,
    "おかしい": 0.002,
    "たのしい": 0.002,
    "悲しい": 0.002
  }
}