{
  "収集": {
    "長い": 0.01,
    "ない": 0.078,
    "いい": 0.046,
    "痛い": 0.002,
    "懐かしい": 0.004,
    "欲しい": 0.016,
    "うい": 0.006,
    "ほしい": 0.018,
    "うまい": 0.01,
    "詳しい": 0.002,
    "良い": 0.038,
    "黒い": 0.006,
    "楽しい": 0.03,
    "面白い": 0.01,
    "えげつない": 0.002,
    "つらい": 0.004,
    "多い": 0.028,
    "凄い": 0.008,
    "やすい": 0.002,
    "無い": 0.026,
    "くさい": 0.002,
    "若い": 0.004,
    "青い": 0.002,
    "おもんない": 0.002,
    "っぽい": 0.008,
    "強い": 0.008,
    "怖い": 0.008,
    "美味しい": 0.008,
    "おもろい": 0.004,
    "すごい": 0.01,
    "正しい": 0.004,
    "寂しい": 0.004,
    "よい": 0.02,
    "新しい": 0.022,
    "素早い": 0.006,
    "忙しい": 0.004,
    "悲しい": 0.004,
    "やばい": 0.008,
    "細かい": 0.002,
    "ぽい": 0.002,
    "渋い": 0.002,
    "くだらない": 0.002,
    "微笑ましい": 0.002,
    "おかしい": 0.002,
    "恐ろしい": 0.002,
    "弱い": 0.004,
    "興味深い": 0.002,
    "惚れっぽい": 0.002,
    "早い": 0.018,
    "悪い": 0.008,
    "遅い": 0.01,
    "低い": 0.002,
    "可愛い": 0.014,
    "いち早い": 0.002,
    "深い": 0.004,
    "ちょろい": 0.002,
    "甘い": 0.004,
    "かわいい": 0.004,
    "小さい": 0.002,
    "柔らかい": 0.002,
    "重い": 0.002,
    "めんどくさい": 0.002,
    "宜しい": 0.002,
    "しんどい": 0.004,
    "嬉しい": 0.01,
    "あぶない": 0.002,
    "下らない": 0.002,
    "ままならない": 0.002,
    "古い": 0.006,
    "にくい": 0.002,
    "大きい": 0.004,
    "高い": 0.014,
    "疑わしい": 0.002,
    "かっこいい": 0.002,
    "有難い": 0.002,
    "うれしい": 0.002,
    "大人しい": 0.002,
    "厳しい": 0.002,
    "汚い": 0.006,
    "重たい": 0.002,
    "少ない": 0.004,
    "はやい": 0.002,
    "すい": 0.002,
    "ありがたい": 0.004,
    "難しい": 0.012,
    "心強い": 0.002,
    "美しい": 0.002,
    "近い": 0.002,
    "辛い": 0.002,
    "眠い": 0.002,
    "温かい": 0.002,
    "短い": 0.002,
    "酷い": 0.002,
    "優しい": 0.002,
    "幼い": 0.002,
    "たまらない": 0.002,
    "よろしい": 0.002,
    "賢い": 0.002,
    "残り少ない": 0.002,
    "狭い": 0.002,
    "明るい": 0.004,
    "申し訳ない": 0.002,
    "悔しい": 0.002,
    "何気ない": 0.002,
    "おおい": 0.004,
    "ええ": 0.002
  }
}