{
  "変遷": {
    "いい": 0.036,
    "凄い": 0.008,
    "ない": 0.07,
    "かわいい": 0.008,
    "くい": 0.002,
    "っぽい": 0.004,
    "すごい": 0.022,
    "寒い": 0.002,
    "太い": 0.002,
    "高い": 0.008,
    "ありがたい": 0.008,
    "宜しい": 0.002,
    "面白い": 0.036,
    "気持ちいい": 0.002,
    "古い": 0.01,
    "薄い": 0.002,
    "激しい": 0.02,
    "青い": 0.002,
    "楽しい": 0.028,
    "よい": 0.012,
    "幽い": 0.002,
    "尊い": 0.002,
    "強い": 0.008,
    "感慨深い": 0.004,
    "厳しい": 0.002,
    "近い": 0.004,
    "早い": 0.008,
    "重い": 0.002,
    "良い": 0.028,
    "多い": 0.024,
    "易い": 0.002,
    "安い": 0.002,
    "たらしい": 0.002,
    "遅い": 0.002,
    "づらい": 0.006,
    "気持ち良い": 0.002,
    "やばい": 0.004,
    "おぞましい": 0.002,
    "辛い": 0.004,
    "大きい": 0.016,
    "可愛い": 0.008,
    "深い": 0.004,
    "おいしい": 0.002,
    "味わい深い": 0.002,
    "美しい": 0.004,
    "新しい": 0.008,
    "申し訳ない": 0.002,
    "賢い": 0.002,
    "おもしろい": 0.002,
    "正しい": 0.006,
    "ほしい": 0.004,
    "軽い": 0.004,
    "つまらない": 0.004,
    "でかい": 0.004,
    "すばらしい": 0.002,
    "眩しい": 0.002,
    "いたい": 0.002,
    "奥深い": 0.002,
    "無い": 0.002,
    "長い": 0.006,
    "弱い": 0.004,
    "小ちゃい": 0.002,
    "やむを得ない": 0.002,
    "儚い": 0.002,
    "嬉しい": 0.004,
    "低い": 0.002,
    "奥ゆかしい": 0.002,
    "ゆかしい": 0.002,
    "うらやましい": 0.002,
    "人間臭い": 0.002,
    "人間らしい": 0.004,
    "明るい": 0.002,
    "懐かしい": 0.006,
    "上手い": 0.004,
    "ゆるい": 0.002,
    "がたい": 0.002,
    "苦しい": 0.002,
    "人らしい": 0.002,
    "若い": 0.002,
    "望ましい": 0.002,
    "つよい": 0.002,
    "短い": 0.002,
    "こわい": 0.004,
    "くだらない": 0.002,
    "痛い": 0.002,
    "有り難い": 0.002,
    "素晴らしい": 0.002,
    "難しい": 0.002,
    "えらい": 0.002,
    "濃い": 0.002,
    "おびただしい": 0.002,
    "丸い": 0.002,
    "悪い": 0.002,
    "興味深い": 0.002,
    "暖かい": 0.002,
    "とおい": 0.002,
    "分厚い": 0.002,
    "やすい": 0.006,
    "羨ましい": 0.002,
    "恋しい": 0.002,
    "切ない": 0.002,
    "赤い": 0.002,
    "広い": 0.002,
    "愛しい": 0.002,
    "しつこい": 0.002,
    "勇ましい": 0.002,
    "熱い": 0.002,
    "どでかい": 0.002,
    "やかましい": 0.002,
    "あおい": 0.004
  }
}