{
  "開園": {
    "恐ろしい": 0.002,
    "甲高い": 0.002,
    "うい": 0.002,
    "黒い": 0.002,
    "でっかい": 0.002,
    "無い": 0.002,
    "明るい": 0.004,
    "優しい": 0.004,
    "あたたかい": 0.002,
    "眠い": 0.002,
    "こい": 0.002,
    "めでたい": 0.002,
    "いい": 0.042,
    "あしい": 0.002,
    "すごい": 0.008,
    "よい": 0.026,
    "多い": 0.022,
    "ない": 0.054,
    "おしい": 0.002,
    "悪い": 0.006,
    "暖かい": 0.002,
    "強い": 0.006,
    "嬉しい": 0.008,
    "青い": 0.002,
    "可愛い": 0.01,
    "楽しい": 0.008,
    "やすい": 0.006,
    "ださい": 0.004,
    "近い": 0.008,
    "長い": 0.008,
    "早い": 0.02,
    "少ない": 0.004,
    "かわいい": 0.012,
    "づらい": 0.002,
    "良い": 0.026,
    "欲しい": 0.018,
    "広い": 0.004,
    "遠い": 0.002,
    "難しい": 0.004,
    "新しい": 0.006,
    "遅い": 0.01,
    "おもろい": 0.002,
    "つらい": 0.002,
    "安い": 0.002,
    "よろしい": 0.002,
    "丸い": 0.002,
    "ゆるい": 0.002,
    "おかしい": 0.002,
    "寂しい": 0.002,
    "軽い": 0.002,
    "くろい": 0.008,
    "濃い": 0.002,
    "きつい": 0.002,
    "短い": 0.008,
    "しろい": 0.002,
    "気持ちいい": 0.002,
    "円い": 0.002,
    "危ない": 0.002,
    "ほしい": 0.008,
    "面白い": 0.004,
    "うまい": 0.004,
    "凄い": 0.002,
    "素晴らしい": 0.004,
    "偉い": 0.002,
    "物凄い": 0.002,
    "怖い": 0.002,
    "険しい": 0.002,
    "苦しい": 0.002,
    "面倒くさい": 0.002,
    "懐かしい": 0.002,
    "弱い": 0.002,
    "遠慮ない": 0.002,
    "重い": 0.002,
    "おそい": 0.002,
    "美味しい": 0.006,
    "狭い": 0.002,
    "ふるい": 0.002,
    "おおい": 0.002,
    "ありがたい": 0.002,
    "宜しい": 0.002,
    "乏しい": 0.002,
    "古い": 0.002
  }
}